dynamo_store/__init__.py
dynamo_store/aescrypt.py
dynamo_store/log.py
dynamo_store/object.py
dynamo_store/store.py
dynamo_store/util.py
tests/__init__.py
tests/test_crypto.py
tests/test_object.py
tests/test_store.py
tests/test_util.py
dynamo_store-0.6.0.dist-info/LICENSE
dynamo_store-0.6.0.dist-info/METADATA
dynamo_store-0.6.0.dist-info/WHEEL
dynamo_store-0.6.0.dist-info/top_level.txt
dynamo_store-0.6.0.dist-info/zip-safe
dynamo_store-0.6.0.dist-info/RECORD
