Metadata-Version: 2.1
Name: dynamo-store
Version: 0.6.0
Summary: dynamo-store is designed to make multi-sharded data storage in DynamoDB seamless
Home-page: https://github.com/GusBricker/dynamo-store
Author: Chris Lapa
Author-email: chris@lapa.com.au
License: GPLv2
Keywords: dynamo,store,JSON,shard,encryption,dynamodb,aws
Platform: UNKNOWN
Classifier: Development Status :: 4 - Beta
Classifier: Intended Audience :: Developers
Classifier: Intended Audience :: Science/Research
Classifier: License :: OSI Approved :: GNU General Public License v2 (GPLv2)
Classifier: Programming Language :: Python
Classifier: Topic :: Software Development :: Libraries :: Python Modules
Requires-Python: >=3
Requires-Dist: jsonpath-ng
Requires-Dist: boto3
Requires-Dist: pycrypto
Requires-Dist: jsonmodels
